submodlib_cpp.cpython-311-x86_64-linux-musl.so
submodlib/__init__.py
submodlib/helper.py
submodlib/myfunctions.py
submodlib/optimizers.py.old
submodlib/version.py
submodlib/functions/__init__.py
submodlib/functions/clustered.py
submodlib/functions/concaveOverModular.py
submodlib/functions/conditionalGain.py.old
submodlib/functions/conditionalMutualInformation.py.old
submodlib/functions/disparityMin.py
submodlib/functions/disparitySum.py
submodlib/functions/facilityLocation.py
submodlib/functions/facilityLocation.py.numpy
submodlib/functions/facilityLocationConditionalGain.py
submodlib/functions/facilityLocationConditionalMutualInformation.py
submodlib/functions/facilityLocationMutualInformation.py
submodlib/functions/facilityLocationVariantMutualInformation.py
submodlib/functions/featureBased.py
submodlib/functions/graphCut.py
submodlib/functions/graphCutConditionalGain.py
submodlib/functions/graphCutMutualInformation.py
submodlib/functions/logDeterminant.py
submodlib/functions/logDeterminantConditionalGain.py
submodlib/functions/logDeterminantConditionalMutualInformation.py
submodlib/functions/logDeterminantMutualInformation.py
submodlib/functions/mixture.py
submodlib/functions/probabilisticSetCover.py
submodlib/functions/probabilisticSetCoverConditionalGain.py
submodlib/functions/probabilisticSetCoverConditionalMutualInformation.py
submodlib/functions/probabilisticSetCoverMutualInformation.py
submodlib/functions/saturatedCoverage.py
submodlib/functions/setCover.py
submodlib/functions/setCoverConditionalGain.py
submodlib/functions/setCoverConditionalMutualInformation.py
submodlib/functions/setCoverMutualInformation.py
submodlib/functions/setFunction.py
submodlib/functions/submodularMutualInformation.py.old
submodlib_py.libs/libgcc_s-2298274a.so.1
submodlib_py.libs/libstdc++-08d5c7eb.so.6.0.33
submodlib_py-0.0.3.dist-info/METADATA
submodlib_py-0.0.3.dist-info/WHEEL
submodlib_py-0.0.3.dist-info/top_level.txt
submodlib_py-0.0.3.dist-info/RECORD
submodlib_py-0.0.3.dist-info/licenses/LICENSE
