Metadata-Version: 2.1
Name: submodlib-py
Version: 0.0.3
Summary: SubModLib is an easy-to-use, efficient and scalable Python library for submodular optimization with a C++ optimization engine. Submodlib finds its application in summarization, data subset selection, hyper parameter tuning, efficient training etc. Through a rich API, it offers a great deal of flexibility in the way it can be used.
Home-page: https://github.com/vishkaush/submodlib
Author: Vishal Kaushal, Krishnateja Killamsetty, Suraj Kothawade, Rishabh Iyer
Author-email: Vishal Kaushal <vkaushal@cse.iitb.ac.in>, Krishnateja Killamsetty <krishnateja.k@ibm.com>, Suraj Kothawade <skothawade@google.com>, Ganesh Ramakrishnan <ganesh@cse.iitb.ac.in>, Rishabh Iyer <rishabh.iyer@utdallas.edu>
License: MIT License
Project-URL: Homepage, https://github.com/decile-team/submodlib
Project-URL: Issues, https://github.com/decile-team/submodlib/issues
Classifier: Programming Language :: Python :: 3
Classifier: Operating System :: OS Independent
Classifier: License :: OSI Approved :: MIT License
Requires-Python: >=3.8
License-File: LICENSE
Requires-Dist: numpy>=1.24.4
Requires-Dist: numba>=0.43.0
Requires-Dist: scipy
Requires-Dist: scikit-learn
Requires-Dist: matplotlib
Requires-Dist: tqdm
Requires-Dist: pandas
Requires-Dist: joblib
